{
  "error": null,
  "http_status": 200,
  "request_identity": "doi:10.1007/978-3-642-21997-9_36",
  "response_body_utf8": "{\"status\":\"ok\",\"message-type\":\"work\",\"message-version\":\"1.0.0\",\"message\":{\"indexed\":{\"date-parts\":[[2024,9,6]],\"date-time\":\"2024-09-06T21:13:39Z\",\"timestamp\":1725657219769},\"publisher-location\":\"Berlin, Heidelberg\",\"reference-count\":23,\"publisher\":\"Springer Berlin Heidelberg\",\"isbn-type\":[{\"type\":\"print\",\"value\":\"9783642219962\"},{\"type\":\"electronic\",\"value\":\"9783642219979\"}],\"content-domain\":{\"domain\":[],\"crossmark-restriction\":false},\"short-container-title\":[],\"published-print\":{\"date-parts\":[[2012]]},\"DOI\":\"10.1007\\/978-3-642-21997-9_36\",\"type\":\"book-chapter\",\"created\":{\"date-parts\":[[2012,2,7]],\"date-time\":\"2012-02-07T10:35:25Z\",\"timestamp\":1328610925000},\"page\":\"475-481\",\"source\":\"Crossref\",\"is-referenced-by-count\":1,\"title\":[\"Automated Diagnosis and Reflectance Confocal Microscopy\"],\"prefix\":\"10.1007\",\"author\":[{\"given\":\"Marco\",\"family\":\"Wiltgen\",\"sequence\":\"first\",\"affiliation\":[],\"role\":[{\"role\":\"author\",\"vocabulary\":\"crossref\"}]}],\"member\":\"297\",\"published-online\":{\"date-parts\":[[2011,11,28]]},\"reference\":[{\"key\":\"36_CR1_36\",\"doi-asserted-by\":\"publisher\",\"first-page\":\"293\",\"DOI\":\"10.1046\\/j.1523-1747.1999.00690.x\",\"volume\":\"113\",\"author\":\"M Rajadhyaksha\",\"year\":\"1999\",\"unstructured\":\"Rajadhyaksha M, Conzales S, Zavislan JM, Anderson RR, Webb RR (1999) In vivo confocal scanning laser microscopy of human skin: advances in instrumentation and comparison with histology. J Invest Dermatol 113:293\\u2013303\",\"journal-title\":\"J Invest Dermatol\"},{\"key\":\"36_CR2_36\",\"doi-asserted-by\":\"publisher\",\"first-page\":\"vii\",\"DOI\":\"10.1111\\/j.0022-202X.2005.23865.x\",\"volume\":\"125\",\"author\":\"KJ Busam\",\"year\":\"2005\",\"unstructured\":\"Busam KJ, Marghoob AA, Halpern AC (2005) Melanoma diagnosis by confocal microscopy: promise and pitfalls. J Invest Dermatol 125:vii\",\"journal-title\":\"J Invest Dermatol\"},{\"key\":\"36_CR3_36\",\"doi-asserted-by\":\"publisher\",\"first-page\":\"365\",\"DOI\":\"10.1067\\/mjd.2001.117395\",\"volume\":\"45\",\"author\":\"RG Langley\",\"year\":\"2001\",\"unstructured\":\"Langley RG, Rajadhyaksha M, Dwyer PJ, Sober AJ, Flotte TJ, Anderson RR (2001) Confocal scanning laser microscopy of benign and malignant skin lesions in vivo. J Am Acad Dermatol 45:365\\u2013376\",\"journal-title\":\"J Am Acad Dermatol\"},{\"key\":\"36_CR4_36\",\"doi-asserted-by\":\"publisher\",\"first-page\":\"532\",\"DOI\":\"10.1111\\/j.0022-202X.2005.23813.x\",\"volume\":\"125\",\"author\":\"G Pellacani\",\"year\":\"2005\",\"unstructured\":\"Pellacani G, Cesinaro AM, Seidenari S (2005) Reflectance-mode confocal microscopy for the in vivo characterization of pagetoid melanocytosis in melanomas and nevi. J Invest Dermatol 125:532\\u2013537\",\"journal-title\":\"J Invest Dermatol\"},{\"key\":\"36_CR5_36\",\"doi-asserted-by\":\"publisher\",\"first-page\":\"493\",\"DOI\":\"10.1111\\/j.0022-202X.2004.23569.x\",\"volume\":\"124\",\"author\":\"A Gerger\",\"year\":\"2005\",\"unstructured\":\"Gerger A, Koller S, Kern T et al (2005) Diagnostic applicability of in vivo confocal laser scanning microscopy in melanocytic skin tumors. J Invest Dermatol 124:493\\u2013498\",\"journal-title\":\"J Invest Dermatol\"},{\"key\":\"36_CR6_36\",\"doi-asserted-by\":\"publisher\",\"first-page\":\"17\",\"DOI\":\"10.1111\\/j.1600-0846.2005.00092.x\",\"volume\":\"11\",\"author\":\"B Erkol\",\"year\":\"2005\",\"unstructured\":\"Erkol B, Moss RH, Stanley RJ, Stoecker WV, Hvatum E (2005) Automatic lesion boundary detection in dermoscopy images using gradient vector flow snakes. Skin Res Technol 11:17\\u201326\",\"journal-title\":\"Skin Res Technol\"},{\"key\":\"36_CR7_36\",\"doi-asserted-by\":\"publisher\",\"first-page\":\"25\",\"DOI\":\"10.1111\\/j.1600-0846.2007.00181.x\",\"volume\":\"13\",\"author\":\"Z She\",\"year\":\"2007\",\"unstructured\":\"She Z, Liu Y, Damatoa A (2007) Combination of features from skin pattern and ABCD analysis for lesion classification. Skin Res Technol 13:25\\u201333\",\"journal-title\":\"Skin Res Technol\"},{\"key\":\"36_CR8_36\",\"doi-asserted-by\":\"publisher\",\"first-page\":\"862\",\"DOI\":\"10.1038\\/modpathol.3880402\",\"volume\":\"14\",\"author\":\"KJ Busam\",\"year\":\"2001\",\"unstructured\":\"Busam KJ, Charles C, Lee G, Halpern AC (2001) Morphologic features of melanocytes, pigmented keratinocytes and melanophages by in vivo confocal scanning laser microscopy. Mod Pathol 14:862\\u2013868\",\"journal-title\":\"Mod Pathol\"},{\"key\":\"36_CR9_36\",\"doi-asserted-by\":\"publisher\",\"first-page\":\"469\",\"DOI\":\"10.1038\\/modpathol.3800330\",\"volume\":\"18\",\"author\":\"G Pellacani\",\"year\":\"2005\",\"unstructured\":\"Pellacani G, Cesinaro AM, Seidenari S (2005) In vivo assessment of melanocytic nests in nevi and melanomas by reflectance confocal microscopy. Mod Pathol 18:469\\u2013474\",\"journal-title\":\"Mod Pathol\"},{\"issue\":\"4\",\"key\":\"36_CR10_36\",\"doi-asserted-by\":\"publisher\",\"first-page\":\"365\",\"DOI\":\"10.1159\\/000109087\",\"volume\":\"215\",\"author\":\"RG Langley\",\"year\":\"2007\",\"unstructured\":\"Langley RG, Walsh N, Sutherland AE, Propperova I, Delaney L, Morris SF, Gallant C (2007) The diagnostic accuracy of in vivo confocal scanning laser microscopy compared to dermoscopy of benign and malignant melanocytic lesions: a prospective study. Dermatology 215(4):365\\u2013372\",\"journal-title\":\"Dermatology\"},{\"issue\":\"2\",\"key\":\"36_CR11_36\",\"doi-asserted-by\":\"publisher\",\"first-page\":\"147\",\"DOI\":\"10.1001\\/archderm.141.2.147\",\"volume\":\"141\",\"author\":\"G Pellacani\",\"year\":\"2005\",\"unstructured\":\"Pellacani G, Cesinaro AM, Longo C, Grana C, Seidenari S (2005) Microscopic in vivo description of cellular architecture of dermoscopic pigment network in nevi and melanomas. Arch Dermatol 141(2):147\\u2013154\",\"journal-title\":\"Arch Dermatol\"},{\"issue\":\"1\",\"key\":\"36_CR12_36\",\"doi-asserted-by\":\"publisher\",\"first-page\":\"88\",\"DOI\":\"10.1016\\/j.jaad.2006.03.009\",\"volume\":\"55\",\"author\":\"RG Langley\",\"year\":\"2006\",\"unstructured\":\"Langley RG, Burton E, Walsh N, Propperova I, Murray SJ (2006) In vivo confocal scanning laser microscopy of benign lentigines: comparison to conventional histology and in vivo characteristics of lentigo maligna. J Am Acad Dermatol 55(1):88\\u201397\",\"journal-title\":\"J Am Acad Dermatol\"},{\"key\":\"36_CR13_36\",\"first-page\":\"15\",\"volume\":\"47\",\"author\":\"M Wiltgen\",\"year\":\"2008\",\"unstructured\":\"Wiltgen M, Gerger A, Wagner C, Smolle J (2008) Automatic identification of diagnostic significant regions in confocal laser scanning microscopy of melanocytic skin tumours. Methods Inf Med 47:15\\u201325\",\"journal-title\":\"Methods Inf Med\"},{\"key\":\"36_CR14_36\",\"first-page\":\"591\",\"volume-title\":\"Numerical recipes in C: the art of scientific computing\",\"author\":\"WH Press\",\"year\":\"1992\",\"unstructured\":\"Press WH, Teukolsky SA, Vetterling WT, Flannery BP (1992) Numerical recipes in C: the art of scientific computing, 2nd edn. Cambridge University Press, New York, pp 591\\u2013606\",\"edition\":\"2\"},{\"key\":\"36_CR15_36\",\"volume-title\":\"Wavelet analysis with applications to image processing\",\"author\":\"L Prasad\",\"year\":\"1997\",\"unstructured\":\"Prasad L, Iyengar SS (1997) Wavelet analysis with applications to image processing. CRC Press, Boca Raton\"},{\"key\":\"36_CR16_36\",\"doi-asserted-by\":\"publisher\",\"first-page\":\"473\",\"DOI\":\"10.1016\\/S1386-5056(01)00198-8\",\"volume\":\"64\",\"author\":\"J Puniena\",\"year\":\"2001\",\"unstructured\":\"Puniena J, Punys V, Punys J (2001) Ultrasound and angio image compression by cosine and wavelet transforms. Int J Med Inform 64:473\\u2013481\",\"journal-title\":\"Int J Med Inform\"},{\"issue\":\"3\",\"key\":\"36_CR17_36\",\"doi-asserted-by\":\"publisher\",\"first-page\":\"117\",\"DOI\":\"10.1007\\/s10278-001-0010-3\",\"volume\":\"14\",\"author\":\"C Mello-Thoms\",\"year\":\"2001\",\"unstructured\":\"Mello-Thoms C, Dunn SM, Nodine CF, Kundel HL (2001) An analysis of perceptual errors in reading mammograms using quasi-local spatial frequency spectra. J Digital Imaging 14(3):117\\u2013123\",\"journal-title\":\"J Digital Imaging\"},{\"issue\":\"4\",\"key\":\"36_CR18_36\",\"doi-asserted-by\":\"publisher\",\"first-page\":\"178\",\"DOI\":\"10.1007\\/BF03168393\",\"volume\":\"13\",\"author\":\"S Terae\",\"year\":\"2000\",\"unstructured\":\"Terae S, Miyasaka K, Kudoh K, Nambu T, Shimizu T, Kaneko K, Yoshikawa H, Kishimoto R, Omatsu T, Fujita N (2000) Wavelet compression on detection of brain lesions with magnetic resonance imaging. J Digital Imaging 13(4):178\\u2013190\",\"journal-title\":\"J Digital Imaging\"},{\"issue\":\"9\",\"key\":\"36_CR19_36\",\"doi-asserted-by\":\"publisher\",\"first-page\":\"1445\",\"DOI\":\"10.1016\\/S0301-5629(00)00289-1\",\"volume\":\"26\",\"author\":\"EK Kerut\",\"year\":\"2000\",\"unstructured\":\"Kerut EK, Given MB, Mc Ilwain E, Allen G, Espinoza C, Giles TD (2000) Echocardio-graphic texture analysis using the wavelet transform: Differentiation of early heart muscle disease. Ultrasound Med Biol 26(9):1445\\u20131453\",\"journal-title\":\"Ultrasound Med Biol\"},{\"key\":\"36_CR20_36\",\"volume-title\":\"Vision\",\"author\":\"D Marr\",\"year\":\"1982\",\"unstructured\":\"Marr D (1982) Vision. W.H. Freeman, New York\"},{\"key\":\"36_CR21_36\",\"volume-title\":\"Learning machines\",\"author\":\"NJ Nilsson\",\"year\":\"1965\",\"unstructured\":\"Nilsson NJ (1965) Learning machines. McGraw Hill, New York\"},{\"issue\":\"1\",\"key\":\"36_CR22_36\",\"first-page\":\"81\",\"volume\":\"1\",\"author\":\"JR Quinlan\",\"year\":\"1986\",\"unstructured\":\"Quinlan JR (1986) Induction of decision trees. Machine Learning 1(1):81\\u2013106\",\"journal-title\":\"Machine Learning\"},{\"key\":\"36_CR23_36\",\"volume-title\":\"C4.5: Programs for machine learning\",\"author\":\"JR Quinlan\",\"year\":\"1993\",\"unstructured\":\"Quinlan JR (1993) C4.5: Programs for machine learning. Morgan Kaufmann, San Francisco\"}],\"container-title\":[\"Reflectance Confocal Microscopy for Skin Diseases\"],\"original-title\":[],\"language\":\"en\",\"link\":[{\"URL\":\"http:\\/\\/link.springer.com\\/content\\/pdf\\/10.1007\\/978-3-642-21997-9_36.pdf\",\"content-type\":\"unspecified\",\"content-version\":\"vor\",\"intended-application\":\"similarity-checking\"}],\"deposited\":{\"date-parts\":[[2021,4,30]],\"date-time\":\"2021-04-30T13:32:52Z\",\"timestamp\":1619789572000},\"score\":1,\"resource\":{\"primary\":{\"URL\":\"http:\\/\\/link.springer.com\\/10.1007\\/978-3-642-21997-9_36\"}},\"subtitle\":[],\"short-title\":[],\"issued\":{\"date-parts\":[[2011,11,28]]},\"ISBN\":[\"9783642219962\",\"9783642219979\"],\"references-count\":23,\"URL\":\"https:\\/\\/doi.org\\/10.1007\\/978-3-642-21997-9_36\",\"relation\":{},\"subject\":[],\"published\":{\"date-parts\":[[2011,11,28]]}}}",
  "retrieved_at_utc": "2026-07-13T08:38:51.098877Z",
  "source": "crossref_doi"
}
