{
  "error": null,
  "http_status": 200,
  "request_identity": "doi:10.1111/ddg.15883",
  "response_body_utf8": "{\"status\":\"ok\",\"message-type\":\"work\",\"message-version\":\"1.0.0\",\"message\":{\"indexed\":{\"date-parts\":[[2026,5,1]],\"date-time\":\"2026-05-01T22:37:44Z\",\"timestamp\":1777675064442,\"version\":\"3.51.4\"},\"reference-count\":145,\"publisher\":\"Wiley\",\"issue\":\"12\",\"license\":[{\"start\":{\"date-parts\":[[2025,11,16]],\"date-time\":\"2025-11-16T00:00:00Z\",\"timestamp\":1763251200000},\"content-version\":\"vor\",\"delay-in-days\":0,\"URL\":\"http:\\/\\/creativecommons.org\\/licenses\\/by\\/4.0\\/\"}],\"content-domain\":{\"domain\":[\"onlinelibrary.wiley.com\"],\"crossmark-restriction\":true},\"short-container-title\":[\"J Deutsche Derma Gesell\"],\"published-print\":{\"date-parts\":[[2025,12]]},\"abstract\":\"<jats:title>Summary<\\/jats:title>\\n                  <jats:p>Non\\u2010invasive imaging techniques allow a quick and easy in vivo examination of the skin with different penetration depths and resolution depending on the applied technology.<\\/jats:p>\\n                  <jats:p>Established methods such as dermoscopy and high\\u2010resolution sonography of the skin have been an integral part of everyday life for decades. Additionally, new emerging techniques such as optical coherence tomography (OCT), reflectance confocal microscopy (RCM), and line\\u2010field confocal OCT (LC\\u2010OCT) have entered clinical practice. Multiphoton tomography and optoacoustic imaging are also considered promising new methods.<\\/jats:p>\\n                  <jats:p>\\n                    RCM and LC\\u2010OCT can also be used\\n                    <jats:italic>ex vivo<\\/jats:italic>\\n                    on freshly excised tissue, for example in Moh's surgery margin assessment.\\n                  <\\/jats:p>\\n                  <jats:p>The data generated by all imaging methods is ideal for the application of AI\\u2010based algorithms to increase diagnostic accuracy and support experienced users.<\\/jats:p>\\n                  <jats:p>All mentioned methods have preferred indications depending on their strengths and limitations, both in skin tumor diagnostics and in inflammatory, infectious and parasitic dermatoses. The following guideline provides an overview of the various devices and techniques, explains how each method works and provides the current study situation with indications and limitations of each procedure.<\\/jats:p>\",\"DOI\":\"10.1111\\/ddg.15883\",\"type\":\"journal-article\",\"created\":{\"date-parts\":[[2025,11,17]],\"date-time\":\"2025-11-17T07:29:57Z\",\"timestamp\":1763364597000},\"page\":\"1616-1630\",\"update-policy\":\"https:\\/\\/doi.org\\/10.1002\\/crossmark_policy\",\"source\":\"Crossref\",\"is-referenced-by-count\":2,\"title\":[\"S1 guideline for imaging diagnostics for skin diseases\"],\"prefix\":\"10.1111\",\"volume\":\"23\",\"author\":[{\"ORCID\":\"https:\\/\\/orcid.org\\/0000-0003-4935-9877\",\"authenticated-orcid\":false,\"given\":\"Maximilian\",\"family\":\"Deu\\u00dfing\",\"sequence\":\"first\",\"affiliation\":[{\"name\":\"Department of Dermatology and Allergy LMU Munich  Munich Germany\"},{\"name\":\"Department of Dermatology Allergology and Laser Medicine Munich Municipal Hospital  Munich Germany\"}],\"role\":[{\"role\":\"author\",\"vocabulary\":\"crossref\"}]},{\"ORCID\":\"https:\\/\\/orcid.org\\/0000-0002-1470-7619\",\"authenticated-orcid\":false,\"given\":\"Sandra\",\"family\":\"Schuh\",\"sequence\":\"additional\",\"affiliation\":[{\"name\":\"Department of Dermatology and Allergology University Hospital Augsburg  Augsburg Germany\"}],\"role\":[{\"role\":\"author\",\"vocabulary\":\"crossref\"}]},{\"given\":\"Janis\",\"family\":\"Thamm\",\"sequence\":\"additional\",\"affiliation\":[{\"name\":\"Department of Dermatology and Allergology University Hospital Augsburg  Augsburg Germany\"}],\"role\":[{\"role\":\"author\",\"vocabulary\":\"crossref\"}]},{\"ORCID\":\"https:\\/\\/orcid.org\\/0009-0007-5902-4989\",\"authenticated-orcid\":false,\"given\":\"Deborah\",\"family\":\"Winkler\",\"sequence\":\"additional\",\"affiliation\":[{\"name\":\"Department of Dermatology and Allergology University Hospital Augsburg  Augsburg Germany\"}],\"role\":[{\"role\":\"author\",\"vocabulary\":\"crossref\"}]},{\"given\":\"Simon\",\"family\":\"Schneider\",\"sequence\":\"additional\",\"affiliation\":[{\"name\":\"Department of Dermatology and Allergology Technical University of Munich  Munich Germany\"}],\"role\":[{\"role\":\"author\",\"vocabulary\":\"crossref\"}]},{\"given\":\"Teresa\",\"family\":\"Nau\",\"sequence\":\"additional\",\"affiliation\":[{\"name\":\"Department of Dermatology and Allergology Technical University of Munich  Munich Germany\"}],\"role\":[{\"role\":\"author\",\"vocabulary\":\"crossref\"}]},{\"given\":\"Ulf\",\"family\":\"Darsow\",\"sequence\":\"additional\",\"affiliation\":[{\"name\":\"Department of Dermatology and Allergology Technical University of Munich  Munich Germany\"}],\"role\":[{\"role\":\"author\",\"vocabulary\":\"crossref\"}]},{\"given\":\"Viktor\",\"family\":\"Schnabel\",\"sequence\":\"additional\",\"affiliation\":[{\"name\":\"Department of Dermatology Venereology and Allergology University Hospital Leipzig  Leipzig Germany\"}],\"role\":[{\"role\":\"author\",\"vocabulary\":\"crossref\"}]},{\"given\":\"Martina\",\"family\":\"Ulrich\",\"sequence\":\"additional\",\"affiliation\":[{\"name\":\"Dermatologie am Regierungsviertel  Berlin Germany\"}],\"role\":[{\"role\":\"author\",\"vocabulary\":\"crossref\"}]},{\"ORCID\":\"https:\\/\\/orcid.org\\/0000-0002-1258-6390\",\"authenticated-orcid\":false,\"given\":\"Lynhda\",\"family\":\"Nguyen\",\"sequence\":\"additional\",\"affiliation\":[{\"name\":\"Department of Dermatology and Venereology University Hospital Hamburg\\u2010Eppendorf (UKE)  Hamburg Germany\"}],\"role\":[{\"role\":\"author\",\"vocabulary\":\"crossref\"}]},{\"given\":\"Denis\",\"family\":\"Frenzel\",\"sequence\":\"additional\",\"affiliation\":[{\"name\":\"Praxisklinik Starnberg  Starnberg Germany\"}],\"role\":[{\"role\":\"author\",\"vocabulary\":\"crossref\"}]},{\"ORCID\":\"https:\\/\\/orcid.org\\/0000-0002-7100-7248\",\"authenticated-orcid\":false,\"given\":\"Chiara\",\"family\":\"Fischer\",\"sequence\":\"additional\",\"affiliation\":[{\"name\":\"Department of Biological Imaging Technical University of Munich  Munich Germany\"}],\"role\":[{\"role\":\"author\",\"vocabulary\":\"crossref\"}]},{\"ORCID\":\"https:\\/\\/orcid.org\\/0000-0002-9860-1095\",\"authenticated-orcid\":false,\"given\":\"Cristel\",\"family\":\"Ruini\",\"sequence\":\"additional\",\"affiliation\":[{\"name\":\"Department of Dermatology and Allergy LMU Munich  Munich Germany\"},{\"name\":\"Department of Dermatology Sapienza University of Rome  Rome Italy\"}],\"role\":[{\"role\":\"author\",\"vocabulary\":\"crossref\"}]},{\"given\":\"Vasilis\",\"family\":\"Ntziachristos\",\"sequence\":\"additional\",\"affiliation\":[{\"name\":\"Institute of Biological and Medical Imaging Helmholtz Center Munich Neuherberg Germany Chair of Biological Imaging Central Institute for Translational Cancer Research (TranslaTUM) School of Medicine Technical University of Munich  Munich Germany\"}],\"role\":[{\"role\":\"author\",\"vocabulary\":\"crossref\"}]},{\"given\":\"Martin\",\"family\":\"Kaatz\",\"sequence\":\"additional\",\"affiliation\":[{\"name\":\"Department of Dermatology DRK Hospital Chemnitz\\u2010Rabenstein  Chemnitz Germany\"}],\"role\":[{\"role\":\"author\",\"vocabulary\":\"crossref\"}]},{\"given\":\"Hjalmar\",\"family\":\"Kurzen\",\"sequence\":\"additional\",\"affiliation\":[{\"name\":\"Freising Skin and Laser Center  Freising Germany\"}],\"role\":[{\"role\":\"author\",\"vocabulary\":\"crossref\"}]},{\"given\":\"Bernd\",\"family\":\"Kardorff\",\"sequence\":\"additional\",\"affiliation\":[{\"name\":\"Group Practice for Dermatology Allergology Phlebology and Laser Medicine Prof. Dr. Kardorff medermis clinics  M\\u00f6nchengladbach Germany\"}],\"role\":[{\"role\":\"author\",\"vocabulary\":\"crossref\"}]},{\"given\":\"Rudolf\",\"family\":\"Herbst\",\"sequence\":\"additional\",\"affiliation\":[{\"name\":\"Department of Dermatology and Allergology Helios Hospital Erfurt  Erfurt Germany\"}],\"role\":[{\"role\":\"author\",\"vocabulary\":\"crossref\"}]},{\"given\":\"Sonja\",\"family\":\"Grunewald\",\"sequence\":\"additional\",\"affiliation\":[{\"name\":\"Department of Dermatology Venereology and Allergology University Hospital Leipzig  Leipzig Germany\"}],\"role\":[{\"role\":\"author\",\"vocabulary\":\"crossref\"}]},{\"given\":\"Elke\",\"family\":\"Sattler\",\"sequence\":\"additional\",\"affiliation\":[{\"name\":\"Department of Dermatology and Allergy LMU Munich  Munich Germany\"}],\"role\":[{\"role\":\"author\",\"vocabulary\":\"crossref\"}]},{\"ORCID\":\"https:\\/\\/orcid.org\\/0000-0002-6099-7418\",\"authenticated-orcid\":false,\"given\":\"Julia\",\"family\":\"Welzel\",\"sequence\":\"additional\",\"affiliation\":[{\"name\":\"Department of Dermatology and Allergology University Hospital Augsburg  Augsburg Germany\"}],\"role\":[{\"role\":\"author\",\"vocabulary\":\"crossref\"}]},{\"given\":\"Daniela\",\"family\":\"Hartmann\",\"sequence\":\"additional\",\"affiliation\":[{\"name\":\"Department of Dermatology and Allergy LMU Munich  Munich Germany\"},{\"name\":\"Department of Dermatology Allergology and Laser Medicine Munich Municipal Hospital  Munich Germany\"}],\"role\":[{\"role\":\"author\",\"vocabulary\":\"crossref\"}]}],\"member\":\"311\",\"published-online\":{\"date-parts\":[[2025,11,16]]},\"reference\":[{\"key\":\"e_1_2_12_2_1\",\"doi-asserted-by\":\"publisher\",\"DOI\":\"10.1111\\/1523-1747.ep12606215\"},{\"key\":\"e_1_2_12_3_1\",\"doi-asserted-by\":\"publisher\",\"DOI\":\"10.1001\\/archdermatol.2009.228\"},{\"key\":\"e_1_2_12_4_1\",\"doi-asserted-by\":\"publisher\",\"DOI\":\"10.1016\\/j.jaad.2007.05.044\"},{\"key\":\"e_1_2_12_5_1\",\"doi-asserted-by\":\"publisher\",\"DOI\":\"10.1111\\/jdv.18636\"},{\"key\":\"e_1_2_12_6_1\",\"doi-asserted-by\":\"publisher\",\"DOI\":\"10.1111\\/jdv.16248\"},{\"key\":\"e_1_2_12_7_1\",\"doi-asserted-by\":\"publisher\",\"DOI\":\"10.1111\\/bjd.18722\"},{\"issue\":\"12\",\"key\":\"e_1_2_12_8_1\",\"article-title\":\"Reflectance confocal microscopy for diagnosing cutaneous melanoma in adults\",\"volume\":\"12\",\"author\":\"Dinnes J\",\"year\":\"2018\",\"journal-title\":\"Cochrane Database Syst Rev\"},{\"key\":\"e_1_2_12_9_1\",\"doi-asserted-by\":\"publisher\",\"DOI\":\"10.1001\\/jamadermatol.2022.1570\"},{\"key\":\"e_1_2_12_10_1\",\"doi-asserted-by\":\"publisher\",\"DOI\":\"10.3390\\/cancers14030838\"},{\"key\":\"e_1_2_12_11_1\",\"doi-asserted-by\":\"publisher\",\"DOI\":\"10.1046\\/j.0022-202x.2001.01420.x\"},{\"key\":\"e_1_2_12_12_1\",\"doi-asserted-by\":\"publisher\",\"DOI\":\"10.1067\\/mjd.2002.124690\"},{\"key\":\"e_1_2_12_13_1\",\"doi-asserted-by\":\"publisher\",\"DOI\":\"10.1034\\/j.1600-0846.2002.20345.x\"},{\"key\":\"e_1_2_12_14_1\",\"doi-asserted-by\":\"publisher\",\"DOI\":\"10.1016\\/j.jaad.2005.11.1096\"},{\"key\":\"e_1_2_12_15_1\",\"doi-asserted-by\":\"publisher\",\"DOI\":\"10.1016\\/j.jaad.2009.02.036\"},{\"key\":\"e_1_2_12_16_1\",\"doi-asserted-by\":\"publisher\",\"DOI\":\"10.1111\\/j.1524-4725.2004.30505.x\"},{\"key\":\"e_1_2_12_17_1\",\"doi-asserted-by\":\"publisher\",\"DOI\":\"10.1117\\/1.2750294\"},{\"key\":\"e_1_2_12_18_1\",\"doi-asserted-by\":\"publisher\",\"DOI\":\"10.1016\\/j.jaad.2004.06.028\"},{\"key\":\"e_1_2_12_19_1\",\"doi-asserted-by\":\"publisher\",\"DOI\":\"10.1111\\/j.1600-0560.2010.01632.x\"},{\"key\":\"e_1_2_12_20_1\",\"doi-asserted-by\":\"publisher\",\"DOI\":\"10.1067\\/mjd.2000.105565\"},{\"key\":\"e_1_2_12_21_1\",\"doi-asserted-by\":\"publisher\",\"DOI\":\"10.1111\\/j.1524-4725.2008.34195.x\"},{\"key\":\"e_1_2_12_22_1\",\"doi-asserted-by\":\"publisher\",\"DOI\":\"10.1111\\/j.1365-2133.2007.07865.x\"},{\"key\":\"e_1_2_12_23_1\",\"doi-asserted-by\":\"publisher\",\"DOI\":\"10.1111\\/j.1524-4725.2007.34117.x\"},{\"key\":\"e_1_2_12_24_1\",\"doi-asserted-by\":\"publisher\",\"DOI\":\"10.1111\\/jdv.13215\"},{\"key\":\"e_1_2_12_25_1\",\"doi-asserted-by\":\"publisher\",\"DOI\":\"10.1111\\/j.1365-2133.2011.10563.x\"},{\"key\":\"e_1_2_12_26_1\",\"doi-asserted-by\":\"publisher\",\"DOI\":\"10.1001\\/archdermatol.2009.134\"},{\"key\":\"e_1_2_12_27_1\",\"doi-asserted-by\":\"publisher\",\"DOI\":\"10.1111\\/bjd.13499\"},{\"key\":\"e_1_2_12_28_1\",\"doi-asserted-by\":\"publisher\",\"DOI\":\"10.5070\\/D3263048026\"},{\"key\":\"e_1_2_12_29_1\",\"doi-asserted-by\":\"publisher\",\"DOI\":\"10.1111\\/j.1365-4632.2011.05144.x\"},{\"issue\":\"2\",\"key\":\"e_1_2_12_30_1\",\"first-page\":\"93\",\"article-title\":\"Reflectance confocal microscopy: an effective diagnostic tool for dermatophytic infections\",\"volume\":\"95\",\"author\":\"Friedman D\",\"year\":\"2015\",\"journal-title\":\"Cutis\"},{\"key\":\"e_1_2_12_31_1\",\"doi-asserted-by\":\"publisher\",\"DOI\":\"10.1111\\/j.1600-0846.2012.00615.x\"},{\"key\":\"e_1_2_12_32_1\",\"doi-asserted-by\":\"publisher\",\"DOI\":\"10.1111\\/myc.12333\"},{\"key\":\"e_1_2_12_33_1\",\"doi-asserted-by\":\"publisher\",\"DOI\":\"10.1111\\/j.1439-0507.2012.02198.x\"},{\"key\":\"e_1_2_12_34_1\",\"doi-asserted-by\":\"publisher\",\"DOI\":\"10.1016\\/j.jaad.2014.02.020\"},{\"key\":\"e_1_2_12_35_1\",\"doi-asserted-by\":\"publisher\",\"DOI\":\"10.1111\\/srt.13158\"},{\"key\":\"e_1_2_12_36_1\",\"doi-asserted-by\":\"publisher\",\"DOI\":\"10.1007\\/s10103-011-0894-1\"},{\"key\":\"e_1_2_12_37_1\",\"doi-asserted-by\":\"publisher\",\"DOI\":\"10.1001\\/archderm.141.10.1336\"},{\"key\":\"e_1_2_12_38_1\",\"doi-asserted-by\":\"publisher\",\"DOI\":\"10.1111\\/jdv.13676\"},{\"key\":\"e_1_2_12_39_1\",\"doi-asserted-by\":\"publisher\",\"DOI\":\"10.1111\\/bjd.13783\"},{\"key\":\"e_1_2_12_40_1\",\"doi-asserted-by\":\"publisher\",\"DOI\":\"10.1111\\/j.1365-2133.2012.11096.x\"},{\"key\":\"e_1_2_12_41_1\",\"doi-asserted-by\":\"publisher\",\"DOI\":\"10.1016\\/j.ajo.2019.02.026\"},{\"key\":\"e_1_2_12_42_1\",\"doi-asserted-by\":\"publisher\",\"DOI\":\"10.1159\\/000363289\"},{\"key\":\"e_1_2_12_43_1\",\"doi-asserted-by\":\"publisher\",\"DOI\":\"10.1111\\/bjd.14516\"},{\"key\":\"e_1_2_12_44_1\",\"doi-asserted-by\":\"publisher\",\"DOI\":\"10.1016\\/j.jaad.2003.08.005\"},{\"key\":\"e_1_2_12_45_1\",\"doi-asserted-by\":\"publisher\",\"DOI\":\"10.2310\\/6620.2006.05052\"},{\"key\":\"e_1_2_12_46_1\",\"doi-asserted-by\":\"publisher\",\"DOI\":\"10.1016\\/j.ad.2018.08.008\"},{\"key\":\"e_1_2_12_47_1\",\"doi-asserted-by\":\"publisher\",\"DOI\":\"10.1111\\/j.1600-0846.2011.00577.x\"},{\"issue\":\"6\",\"key\":\"e_1_2_12_48_1\",\"first-page\":\"705\",\"article-title\":\"A comparative study of allergic contact dermatitis by patch test versus reflectance confocal laser microscopy, with nickel and cobalt\",\"volume\":\"20\",\"author\":\"Sakanashi EN\",\"year\":\"2010\",\"journal-title\":\"Eur J Dermatol\"},{\"key\":\"e_1_2_12_49_1\",\"doi-asserted-by\":\"publisher\",\"DOI\":\"10.1111\\/j.0022-202X.2004.23605.x\"},{\"key\":\"e_1_2_12_50_1\",\"doi-asserted-by\":\"publisher\",\"DOI\":\"10.1007\\/s00105-021-04906-1\"},{\"key\":\"e_1_2_12_51_1\",\"doi-asserted-by\":\"publisher\",\"DOI\":\"10.1111\\/bjd.19017\"},{\"key\":\"e_1_2_12_52_1\",\"doi-asserted-by\":\"publisher\",\"DOI\":\"10.1016\\/j.jaad.2019.06.041\"},{\"key\":\"e_1_2_12_53_1\",\"doi-asserted-by\":\"publisher\",\"DOI\":\"10.1111\\/bjd.14658\"},{\"key\":\"e_1_2_12_54_1\",\"doi-asserted-by\":\"publisher\",\"DOI\":\"10.1002\\/jbio.201500335\"},{\"key\":\"e_1_2_12_55_1\",\"doi-asserted-by\":\"publisher\",\"DOI\":\"10.1111\\/bjd.13070\"},{\"key\":\"e_1_2_12_56_1\",\"doi-asserted-by\":\"publisher\",\"DOI\":\"10.1002\\/jbio.201700318\"},{\"key\":\"e_1_2_12_57_1\",\"doi-asserted-by\":\"publisher\",\"DOI\":\"10.1117\\/1.3596742\"},{\"key\":\"e_1_2_12_58_1\",\"doi-asserted-by\":\"publisher\",\"DOI\":\"10.1111\\/jdv.17776\"},{\"key\":\"e_1_2_12_59_1\",\"doi-asserted-by\":\"publisher\",\"DOI\":\"10.1111\\/bjd.17507\"},{\"key\":\"e_1_2_12_60_1\",\"doi-asserted-by\":\"publisher\",\"DOI\":\"10.1111\\/jdv.15243\"},{\"key\":\"e_1_2_12_61_1\",\"doi-asserted-by\":\"publisher\",\"DOI\":\"10.1111\\/ddg.14374\"},{\"key\":\"e_1_2_12_62_1\",\"doi-asserted-by\":\"publisher\",\"DOI\":\"10.1111\\/bjd.12671\"},{\"key\":\"e_1_2_12_63_1\",\"doi-asserted-by\":\"publisher\",\"DOI\":\"10.1002\\/jbio.202100372\"},{\"key\":\"e_1_2_12_64_1\",\"volume-title\":\"Histologic Diagnosis Of Inflammatory Skin Diseases: An Algorithmic Method Based On Pattern Analysis\",\"author\":\"Ackermann BAB\",\"year\":\"2005\"},{\"key\":\"e_1_2_12_65_1\",\"doi-asserted-by\":\"publisher\",\"DOI\":\"10.1111\\/jdv.17006\"},{\"key\":\"e_1_2_12_66_1\",\"doi-asserted-by\":\"publisher\",\"DOI\":\"10.1111\\/1346-8138.16773\"},{\"key\":\"e_1_2_12_67_1\",\"doi-asserted-by\":\"publisher\",\"DOI\":\"10.1055\\/a-1072-7162\"},{\"key\":\"e_1_2_12_68_1\",\"doi-asserted-by\":\"publisher\",\"DOI\":\"10.1016\\/j.jaad.2021.01.044\"},{\"key\":\"e_1_2_12_69_1\",\"doi-asserted-by\":\"publisher\",\"DOI\":\"10.1002\\/jbio.201500124\"},{\"key\":\"e_1_2_12_70_1\",\"doi-asserted-by\":\"publisher\",\"DOI\":\"10.1364\\/BOE.422168\"},{\"key\":\"e_1_2_12_71_1\",\"doi-asserted-by\":\"publisher\",\"DOI\":\"10.1002\\/jbio.202100094\"},{\"key\":\"e_1_2_12_72_1\",\"doi-asserted-by\":\"publisher\",\"DOI\":\"10.1007\\/s00105-021-04908-z\"},{\"issue\":\"7\",\"key\":\"e_1_2_12_73_1\",\"first-page\":\"499\",\"article-title\":\"[Optical coherence tomography]\",\"volume\":\"66\",\"author\":\"Braunmuhl T\",\"year\":\"2015\",\"journal-title\":\"Hautarzt\"},{\"key\":\"e_1_2_12_74_1\",\"doi-asserted-by\":\"publisher\",\"DOI\":\"10.1034\\/j.1600-0846.2001.007001001.x\"},{\"key\":\"e_1_2_12_75_1\",\"doi-asserted-by\":\"publisher\",\"DOI\":\"10.1117\\/1.JBO.18.6.061224\"},{\"key\":\"e_1_2_12_76_1\",\"doi-asserted-by\":\"publisher\",\"DOI\":\"10.1007\\/s13555-017-0175-4\"},{\"key\":\"e_1_2_12_77_1\",\"doi-asserted-by\":\"publisher\",\"DOI\":\"10.1111\\/jdv.17969\"},{\"key\":\"e_1_2_12_78_1\",\"doi-asserted-by\":\"publisher\",\"DOI\":\"10.1111\\/jdv.13003\"},{\"key\":\"e_1_2_12_79_1\",\"doi-asserted-by\":\"publisher\",\"DOI\":\"10.1111\\/ddg.14048\"},{\"key\":\"e_1_2_12_80_1\",\"doi-asserted-by\":\"publisher\",\"DOI\":\"10.1016\\/j.pdpdt.2017.02.003\"},{\"key\":\"e_1_2_12_81_1\",\"doi-asserted-by\":\"publisher\",\"DOI\":\"10.1111\\/exd.13036\"},{\"key\":\"e_1_2_12_82_1\",\"doi-asserted-by\":\"publisher\",\"DOI\":\"10.1007\\/s10103-018-2696-1\"},{\"key\":\"e_1_2_12_83_1\",\"doi-asserted-by\":\"publisher\",\"DOI\":\"10.1111\\/bjd.19553\"},{\"key\":\"e_1_2_12_84_1\",\"doi-asserted-by\":\"publisher\",\"DOI\":\"10.1111\\/jdv.17080\"},{\"key\":\"e_1_2_12_85_1\",\"doi-asserted-by\":\"publisher\",\"DOI\":\"10.1111\\/exd.13783\"},{\"key\":\"e_1_2_12_86_1\",\"doi-asserted-by\":\"publisher\",\"DOI\":\"10.1111\\/ced.14762\"},{\"key\":\"e_1_2_12_87_1\",\"doi-asserted-by\":\"publisher\",\"DOI\":\"10.3390\\/cancers14041082\"},{\"key\":\"e_1_2_12_88_1\",\"doi-asserted-by\":\"publisher\",\"DOI\":\"10.1111\\/jdv.17078\"},{\"key\":\"e_1_2_12_89_1\",\"doi-asserted-by\":\"publisher\",\"DOI\":\"10.1111\\/jdv.17603\"},{\"key\":\"e_1_2_12_90_1\",\"doi-asserted-by\":\"publisher\",\"DOI\":\"10.1111\\/srt.13215\"},{\"key\":\"e_1_2_12_91_1\",\"doi-asserted-by\":\"publisher\",\"DOI\":\"10.1111\\/jdv.17548\"},{\"key\":\"e_1_2_12_92_1\",\"doi-asserted-by\":\"publisher\",\"DOI\":\"10.3390\\/cancers13122856\"},{\"key\":\"e_1_2_12_93_1\",\"doi-asserted-by\":\"publisher\",\"DOI\":\"10.1111\\/jdv.17180\"},{\"key\":\"e_1_2_12_94_1\",\"doi-asserted-by\":\"publisher\",\"DOI\":\"10.3390\\/cancers14051140\"},{\"key\":\"e_1_2_12_95_1\",\"doi-asserted-by\":\"publisher\",\"DOI\":\"10.1111\\/srt.12949\"},{\"key\":\"e_1_2_12_96_1\",\"doi-asserted-by\":\"publisher\",\"DOI\":\"10.1111\\/ced.15383\"},{\"key\":\"e_1_2_12_97_1\",\"doi-asserted-by\":\"publisher\",\"DOI\":\"10.1002\\/jbio.202000449\"},{\"key\":\"e_1_2_12_98_1\",\"doi-asserted-by\":\"publisher\",\"DOI\":\"10.1111\\/jdv.18324\"},{\"key\":\"e_1_2_12_99_1\",\"doi-asserted-by\":\"publisher\",\"DOI\":\"10.1111\\/jdv.18293\"},{\"key\":\"e_1_2_12_100_1\",\"doi-asserted-by\":\"publisher\",\"DOI\":\"10.1016\\/j.jdermsci.2009.06.008\"},{\"key\":\"e_1_2_12_101_1\",\"doi-asserted-by\":\"publisher\",\"DOI\":\"10.1007\\/s00105-015-3626-9\"},{\"key\":\"e_1_2_12_102_1\",\"doi-asserted-by\":\"publisher\",\"DOI\":\"10.1002\\/jbio.200710022\"},{\"key\":\"e_1_2_12_103_1\",\"doi-asserted-by\":\"publisher\",\"DOI\":\"10.1088\\/2050-6120\\/ab8808\"},{\"key\":\"e_1_2_12_104_1\",\"doi-asserted-by\":\"publisher\",\"DOI\":\"10.1111\\/exd.12912\"},{\"key\":\"e_1_2_12_105_1\",\"doi-asserted-by\":\"publisher\",\"DOI\":\"10.1111\\/srt.12168\"},{\"key\":\"e_1_2_12_106_1\",\"doi-asserted-by\":\"publisher\",\"DOI\":\"10.1111\\/j.1600-0846.2010.00437.x\"},{\"key\":\"e_1_2_12_107_1\",\"doi-asserted-by\":\"publisher\",\"DOI\":\"10.1016\\/j.sder.2009.06.007\"},{\"key\":\"e_1_2_12_108_1\",\"doi-asserted-by\":\"publisher\",\"DOI\":\"10.1038\\/sj.jid.5701139\"},{\"key\":\"e_1_2_12_109_1\",\"doi-asserted-by\":\"publisher\",\"DOI\":\"10.1111\\/j.1600-0846.2012.00661.x\"},{\"key\":\"e_1_2_12_110_1\",\"doi-asserted-by\":\"publisher\",\"DOI\":\"10.1111\\/j.1600-0625.2012.01554.x\"},{\"key\":\"e_1_2_12_111_1\",\"doi-asserted-by\":\"publisher\",\"DOI\":\"10.1038\\/jid.2008.439\"},{\"key\":\"e_1_2_12_112_1\",\"doi-asserted-by\":\"publisher\",\"DOI\":\"10.1016\\/j.pdpdt.2021.102266\"},{\"key\":\"e_1_2_12_113_1\",\"doi-asserted-by\":\"publisher\",\"DOI\":\"10.1111\\/srt.12035\"},{\"key\":\"e_1_2_12_114_1\",\"doi-asserted-by\":\"publisher\",\"DOI\":\"10.1371\\/journal.pone.0070682\"},{\"key\":\"e_1_2_12_115_1\",\"doi-asserted-by\":\"publisher\",\"DOI\":\"10.1038\\/srep22789\"},{\"key\":\"e_1_2_12_116_1\",\"doi-asserted-by\":\"publisher\",\"DOI\":\"10.1117\\/1.JBO.25.1.014515\"},{\"key\":\"e_1_2_12_117_1\",\"doi-asserted-by\":\"publisher\",\"DOI\":\"10.1038\\/s41598-020-64937-x\"},{\"key\":\"e_1_2_12_118_1\",\"doi-asserted-by\":\"publisher\",\"DOI\":\"10.1364\\/OE.16.004237\"},{\"key\":\"e_1_2_12_119_1\",\"doi-asserted-by\":\"publisher\",\"DOI\":\"10.1155\\/2008\\/602639\"},{\"key\":\"e_1_2_12_120_1\",\"doi-asserted-by\":\"publisher\",\"DOI\":\"10.1074\\/jbc.M502475200\"},{\"key\":\"e_1_2_12_121_1\",\"doi-asserted-by\":\"publisher\",\"DOI\":\"10.1111\\/j.1365-2133.2012.10988.x\"},{\"key\":\"e_1_2_12_122_1\",\"doi-asserted-by\":\"publisher\",\"DOI\":\"10.1364\\/BOE.5.002405\"},{\"key\":\"e_1_2_12_123_1\",\"doi-asserted-by\":\"publisher\",\"DOI\":\"10.1038\\/s41598-020-65689-4\"},{\"key\":\"e_1_2_12_124_1\",\"article-title\":\"Multimodal multiphoton tomograph using a compact femtosecond fiber laser\",\"author\":\"K\\u00f6nig K\",\"year\":\"2019\",\"journal-title\":\"SPIE\"},{\"key\":\"e_1_2_12_125_1\",\"article-title\":\"Clinical multimodal multiphoton tomography of pigmented skin lesions with an ultracompact femtosecond fiber laser\",\"author\":\"K\\u00f6nig K\",\"year\":\"2020\",\"journal-title\":\"SPIE\"},{\"key\":\"e_1_2_12_126_1\",\"doi-asserted-by\":\"publisher\",\"DOI\":\"10.1016\\/j.clindermatol.2021.12.001\"},{\"key\":\"e_1_2_12_127_1\",\"doi-asserted-by\":\"publisher\",\"DOI\":\"10.1016\\/j.pacs.2019.100144\"},{\"key\":\"e_1_2_12_128_1\",\"doi-asserted-by\":\"publisher\",\"DOI\":\"10.1007\\/s00105-021-04907-0\"},{\"key\":\"e_1_2_12_129_1\",\"doi-asserted-by\":\"publisher\",\"DOI\":\"10.1038\\/s41551-019-0377-4\"},{\"key\":\"e_1_2_12_130_1\",\"doi-asserted-by\":\"publisher\",\"DOI\":\"10.1038\\/s41467-022-30471-9\"},{\"key\":\"e_1_2_12_131_1\",\"doi-asserted-by\":\"publisher\",\"DOI\":\"10.1126\\/scitranslmed.abm8059\"},{\"key\":\"e_1_2_12_132_1\",\"doi-asserted-by\":\"publisher\",\"DOI\":\"10.1016\\/j.pacs.2022.100399\"},{\"key\":\"e_1_2_12_133_1\",\"doi-asserted-by\":\"publisher\",\"DOI\":\"10.1016\\/j.jdermsci.2019.07.003\"},{\"key\":\"e_1_2_12_134_1\",\"doi-asserted-by\":\"publisher\",\"DOI\":\"10.1016\\/j.jid.2018.08.014\"},{\"key\":\"e_1_2_12_135_1\",\"doi-asserted-by\":\"publisher\",\"DOI\":\"10.1126\\/sciadv.1602168\"},{\"key\":\"e_1_2_12_136_1\",\"doi-asserted-by\":\"publisher\",\"DOI\":\"10.2147\\/CCID.S316060\"},{\"key\":\"e_1_2_12_137_1\",\"doi-asserted-by\":\"publisher\",\"DOI\":\"10.1002\\/advs.202004226\"},{\"key\":\"e_1_2_12_138_1\",\"doi-asserted-by\":\"publisher\",\"DOI\":\"10.1001\\/archdermatol.2010.302\"},{\"key\":\"e_1_2_12_139_1\",\"doi-asserted-by\":\"publisher\",\"DOI\":\"10.1067\\/mjd.2001.110395\"},{\"key\":\"e_1_2_12_140_1\",\"doi-asserted-by\":\"publisher\",\"DOI\":\"10.1088\\/0031-9155\\/50\\/8\\/004\"},{\"key\":\"e_1_2_12_141_1\",\"doi-asserted-by\":\"publisher\",\"DOI\":\"10.3390\\/jcm11010189\"},{\"key\":\"e_1_2_12_142_1\",\"doi-asserted-by\":\"publisher\",\"DOI\":\"10.1016\\/0022-2860(95)08544-6\"},{\"key\":\"e_1_2_12_143_1\",\"doi-asserted-by\":\"publisher\",\"DOI\":\"10.1126\\/science.1197236\"},{\"key\":\"e_1_2_12_144_1\",\"doi-asserted-by\":\"publisher\",\"DOI\":\"10.1016\\/j.jaad.2018.11.042\"},{\"key\":\"e_1_2_12_145_1\",\"doi-asserted-by\":\"publisher\",\"DOI\":\"10.1016\\/j.jaad.2018.11.043\"},{\"key\":\"e_1_2_12_146_1\",\"doi-asserted-by\":\"publisher\",\"DOI\":\"10.1016\\/j.jaad.2022.06.1166\"}],\"container-title\":[\"JDDG: Journal der Deutschen Dermatologischen Gesellschaft\"],\"original-title\":[],\"language\":\"en\",\"link\":[{\"URL\":\"https:\\/\\/onlinelibrary.wiley.com\\/doi\\/pdf\\/10.1111\\/ddg.15883\",\"content-type\":\"unspecified\",\"content-version\":\"vor\",\"intended-application\":\"similarity-checking\"}],\"deposited\":{\"date-parts\":[[2025,12,11]],\"date-time\":\"2025-12-11T14:14:36Z\",\"timestamp\":1765462476000},\"score\":1,\"resource\":{\"primary\":{\"URL\":\"https:\\/\\/onlinelibrary.wiley.com\\/doi\\/10.1111\\/ddg.15883\"}},\"subtitle\":[],\"short-title\":[],\"issued\":{\"date-parts\":[[2025,11,16]]},\"references-count\":145,\"journal-issue\":{\"issue\":\"12\",\"published-print\":{\"date-parts\":[[2025,12]]}},\"alternative-id\":[\"10.1111\\/ddg.15883\"],\"URL\":\"https:\\/\\/doi.org\\/10.1111\\/ddg.15883\",\"archive\":[\"Portico\"],\"relation\":{},\"ISSN\":[\"1610-0379\",\"1610-0387\"],\"issn-type\":[{\"value\":\"1610-0379\",\"type\":\"print\"},{\"value\":\"1610-0387\",\"type\":\"electronic\"}],\"subject\":[],\"published\":{\"date-parts\":[[2025,11,16]]},\"assertion\":[{\"value\":\"2025-06-03\",\"order\":0,\"name\":\"received\",\"label\":\"Received\",\"group\":{\"name\":\"publication_history\",\"label\":\"Publication History\"}},{\"value\":\"2025-06-12\",\"order\":2,\"name\":\"accepted\",\"label\":\"Accepted\",\"group\":{\"name\":\"publication_history\",\"label\":\"Publication History\"}},{\"value\":\"2025-11-16\",\"order\":3,\"name\":\"published\",\"label\":\"Published\",\"group\":{\"name\":\"publication_history\",\"label\":\"Publication History\"}}]}}",
  "retrieved_at_utc": "2026-07-13T08:28:19.633776Z",
  "source": "crossref_doi"
}
